pydown/__init__.py
pydown/__main__.py
pydown/main.py
MultiPyDown-0.0.2.dist-info/METADATA
MultiPyDown-0.0.2.dist-info/WHEEL
MultiPyDown-0.0.2.dist-info/entry_points.txt
MultiPyDown-0.0.2.dist-info/top_level.txt
MultiPyDown-0.0.2.dist-info/RECORD
