Metadata-Version: 2.1
Name: MultiPyDown
Version: 0.0.2
Summary: Multi File Downloading
Home-page: UNKNOWN
Author: Iman Bhlool
Author-email: ibhlool7@gmail.com
License: MIT
Platform: UNKNOWN
Classifier: License :: OSI Approved :: MIT License
Classifier: Programming Language :: Python :: 3
Classifier: Programming Language :: Python :: 3.8
Requires-Dist: pysmartdl
